.gitignore
MANIFEST.in
README.md
setup.cfg
setup.py
ansible/ansible.cfg
ansible/ansible_hosts
ansible/site.yml
ansible/group_vars/all
ansible/roles/common/handlers/main.yml
ansible/roles/common/tasks/main.yml
ansible/roles/common/templates/hostname.j2
ansible/roles/common/templates/interfaces.j2
conf/mykvm.yml
mykvm/__init__.py
mykvm/command.py
mykvm/main.py
mykvm/model.py
mykvm/util.py
mykvm.egg-info/PKG-INFO
mykvm.egg-info/SOURCES.txt
mykvm.egg-info/dependency_links.txt
mykvm.egg-info/entry_points.txt
mykvm.egg-info/requires.txt
mykvm.egg-info/top_level.txt
script/vmbuilder.sh