Metadata-Version: 1.0
Name: mykvm
Version: 0.3.6
Summary: mykvm is a vagrant like tool to create multiple kvm instances
Home-page: https://github.com/scottchoi/mykvm
Author: Scott Choi
Author-email: hho.choi@me.com
License: PSF
Keywords: kvm vmbuilder qemu-imge virt-install
Platform: UNKNOWN
